newsie/__init__.py
newsie/config.py
newsie/deliver.py
newsie/generate_pdf.py
newsie/issue.py
newsie/newissue.py
newsie/news.py
newsie/util.py
newsie/weather.py
newsie-0.0.6.dist-info/LICENSE
newsie-0.0.6.dist-info/METADATA
newsie-0.0.6.dist-info/WHEEL
newsie-0.0.6.dist-info/entry_points.txt
newsie-0.0.6.dist-info/top_level.txt
newsie-0.0.6.dist-info/RECORD
