Metadata-Version: 2.1
Name: newsie
Version: 0.0.6
Summary: How about a daily printed newspaper, govna!
Home-page: http://github.com/jjg/newsie
Author: Jason J. Gullickson
Author-email: mr@jasongullickson.com
License: GPL3
Platform: UNKNOWN
Classifier: Programming Language :: Python :: 3
Requires-Python: >=3.6
Requires-Dist: ambient-api
Requires-Dist: pycups
Requires-Dist: feedparser
Requires-Dist: image
Requires-Dist: PyLaTeX
Requires-Dist: qrcode
